{"ATLAS": {"SPRITES":[ 
{"SPRITE" : {"name": "0000","x":1,"y":1,"w":2319,"h":669,"rotated": false}},
{"SPRITE" : {"name": "0001","x":3415,"y":335,"w":26,"h":27,"rotated": false}},
{"SPRITE" : {"name": "0002","x":2574,"y":371,"w":27,"h":39,"rotated": false}},
{"SPRITE" : {"name": "0003","x":3476,"y":224,"w":24,"h":52,"rotated": false}},
{"SPRITE" : {"name": "0004","x":3450,"y":235,"w":25,"h":53,"rotated": false}},
{"SPRITE" : {"name": "0005","x":2889,"y":445,"w":28,"h":52,"rotated": false}},
{"SPRITE" : {"name": "0006","x":4068,"y":222,"w":26,"h":51,"rotated": false}},
{"SPRITE" : {"name": "0007","x":3471,"y":163,"w":21,"h":60,"rotated": false}},
{"SPRITE" : {"name": "0008","x":3450,"y":163,"w":20,"h":71,"rotated": false}},
{"SPRITE" : {"name": "0009","x":4061,"y":338,"w":22,"h":75,"rotated": false}},
{"SPRITE" : {"name": "0010","x":4039,"y":338,"w":21,"h":87,"rotated": false}},
{"SPRITE" : {"name": "0011","x":4067,"y":1,"w":21,"h":108,"rotated": false}},
{"SPRITE" : {"name": "0012","x":4068,"y":110,"w":19,"h":111,"rotated": false}},
{"SPRITE" : {"name": "0013","x":3126,"y":163,"w":323,"h":171,"rotated": false}},
{"SPRITE" : {"name": "0014","x":3503,"y":147,"w":356,"h":156,"rotated": false}},
{"SPRITE" : {"name": "0015","x":3503,"y":1,"w":388,"h":145,"rotated": false}},
{"SPRITE" : {"name": "0016","x":3471,"y":224,"w":4,"h":4,"rotated": false}},
{"SPRITE" : {"name": "0017","x":2747,"y":504,"w":3,"h":3,"rotated": false}},
{"SPRITE" : {"name": "0018","x":2457,"y":516,"w":96,"h":14,"rotated": false}},
{"SPRITE" : {"name": "0019","x":3750,"y":487,"w":80,"h":12,"rotated": false}},
{"SPRITE" : {"name": "0020","x":2925,"y":412,"w":74,"h":28,"rotated": false}},
{"SPRITE" : {"name": "0021","x":3987,"y":505,"w":58,"h":46,"rotated": false}},
{"SPRITE" : {"name": "0022","x":4003,"y":274,"w":77,"h":63,"rotated": false}},
{"SPRITE" : {"name": "0023","x":3975,"y":429,"w":93,"h":75,"rotated": false}},
{"SPRITE" : {"name": "0024","x":3713,"y":403,"w":124,"h":83,"rotated": false}},
{"SPRITE" : {"name": "0025","x":3860,"y":274,"w":142,"h":90,"rotated": false}},
{"SPRITE" : {"name": "0026","x":3892,"y":1,"w":174,"h":114,"rotated": false}},
{"SPRITE" : {"name": "0027","x":3860,"y":147,"w":207,"h":126,"rotated": false}},
{"SPRITE" : {"name": "0028","x":2321,"y":371,"w":252,"h":144,"rotated": false}},
{"SPRITE" : {"name": "0029","x":2321,"y":204,"w":290,"h":166,"rotated": false}},
{"SPRITE" : {"name": "0030","x":3535,"y":487,"w":214,"h":34,"rotated": false}},
{"SPRITE" : {"name": "0031","x":3432,"y":522,"w":208,"h":24,"rotated": false}},
{"SPRITE" : {"name": "0032","x":2457,"y":533,"w":195,"h":22,"rotated": false}},
{"SPRITE" : {"name": "0033","x":3892,"y":116,"w":175,"h":26,"rotated": false}},
{"SPRITE" : {"name": "0034","x":3271,"y":495,"w":160,"h":33,"rotated": false}},
{"SPRITE" : {"name": "0035","x":3121,"y":495,"w":149,"h":39,"rotated": false}},
{"SPRITE" : {"name": "0036","x":2321,"y":516,"w":135,"h":46,"rotated": false}},
{"SPRITE" : {"name": "0037","x":2612,"y":267,"w":118,"h":48,"rotated": false}},
{"SPRITE" : {"name": "0038","x":2889,"y":499,"w":119,"h":46,"rotated": false}},
{"SPRITE" : {"name": "0039","x":2765,"y":445,"w":123,"h":62,"rotated": false}},
{"SPRITE" : {"name": "0040","x":2612,"y":204,"w":120,"h":62,"rotated": false}},
{"SPRITE" : {"name": "0041","x":3838,"y":429,"w":136,"h":74,"rotated": false}},
{"SPRITE" : {"name": "0042","x":3188,"y":375,"w":165,"h":71,"rotated": false}},
{"SPRITE" : {"name": "0043","x":3008,"y":375,"w":179,"h":66,"rotated": false}},
{"SPRITE" : {"name": "0044","x":3848,"y":365,"w":190,"h":63,"rotated": false}},
{"SPRITE" : {"name": "0045","x":2925,"y":442,"w":195,"h":56,"rotated": false}},
{"SPRITE" : {"name": "0046","x":2574,"y":445,"w":190,"h":49,"rotated": false}},
{"SPRITE" : {"name": "0047","x":3535,"y":434,"w":174,"h":42,"rotated": false}},
{"SPRITE" : {"name": "0048","x":2574,"y":495,"w":172,"h":37,"rotated": false}},
{"SPRITE" : {"name": "0049","x":2747,"y":508,"w":138,"h":24,"rotated": false}},
{"SPRITE" : {"name": "0050","x":3750,"y":505,"w":236,"h":28,"rotated": false}},
{"SPRITE" : {"name": "0051","x":2653,"y":533,"w":212,"h":19,"rotated": false}},
{"SPRITE" : {"name": "0052","x":2747,"y":495,"w":7,"h":8,"rotated": false}},
{"SPRITE" : {"name": "0053","x":3831,"y":487,"w":5,"h":6,"rotated": false}},
{"SPRITE" : {"name": "0054","x":3471,"y":229,"w":3,"h":4,"rotated": false}},
{"SPRITE" : {"name": "0055","x":3121,"y":473,"w":413,"h":21,"rotated": false}},
{"SPRITE" : {"name": "0056","x":3008,"y":335,"w":406,"h":39,"rotated": false}},
{"SPRITE" : {"name": "0057","x":3450,"y":304,"w":397,"h":62,"rotated": false}},
{"SPRITE" : {"name": "0058","x":2612,"y":317,"w":395,"h":94,"rotated": false}},
{"SPRITE" : {"name": "0059","x":2735,"y":187,"w":379,"h":129,"rotated": false}},
{"SPRITE" : {"name": "0060","x":3126,"y":1,"w":376,"h":161,"rotated": false}},
{"SPRITE" : {"name": "0061","x":2735,"y":1,"w":390,"h":185,"rotated": false}},
{"SPRITE" : {"name": "0062","x":2321,"y":1,"w":413,"h":202,"rotated": false}},
{"SPRITE" : {"name": "0063","x":2574,"y":412,"w":350,"h":32,"rotated": false}},
{"SPRITE" : {"name": "0064","x":3354,"y":403,"w":358,"h":30,"rotated": false}},
{"SPRITE" : {"name": "0065","x":3121,"y":447,"w":368,"h":25,"rotated": false}},
{"SPRITE" : {"name": "0066","x":3415,"y":367,"w":370,"h":35,"rotated": false}},
{"SPRITE" : {"name": "0067","x":3009,"y":535,"w":244,"h":19,"rotated": false}}
]},
"meta": {
"app": "Adobe Animate",
"version": "22.0.5.191",
"image": "spritemap1.png",
"format": "RGBA8888",
"size": {"w":4095,"h":671},
"resolution": "1"
}
}
